commander
tests
