Metadata-Version: 2.1
Name: gcloud-commander
Version: 0.11
Summary: FZF based filemanager for Google Cloud
Home-page: https://github.com/Lonestar137/gcloud-commander
Author: Garrett Jones
Author-email: jonesgc137@gmail.com
Classifier: Programming Language :: Python :: 3
Classifier: Operating System :: Unix
Classifier: Operating System :: MacOS :: MacOS X
Classifier: Operating System :: Microsoft :: Windows
Requires-Python: >=3.5
License-File: LICENSE
